CHANGES.txt
MANIFEST.in
hashish.py
readme.md
setup.cfg
setup.py
hashish.egg-info/PKG-INFO
hashish.egg-info/SOURCES.txt
hashish.egg-info/dependency_links.txt
hashish.egg-info/not-zip-safe
hashish.egg-info/top_level.txt