Metadata-Version: 1.0
Name: hashish
Version: 0.1.1
Summary: Password Hashing Library
Home-page: https://bitbucket.org/russellhay/hashish
Author: Russell Hay
Author-email: me@russellhay.com
License: UNKNOWN
Platform: UNKNOWN
